custodial_registration_proxy/__init__.py
custodial_registration_proxy/custodial_registration_proxy.py
custodial_registration_proxy/data/CustodialRegistrationProxy.bin
custodial_registration_proxy/runnable/publish.py
custodial_registration_proxy-0.3.1.dist-info/LICENSE
custodial_registration_proxy-0.3.1.dist-info/METADATA
custodial_registration_proxy-0.3.1.dist-info/WHEEL
custodial_registration_proxy-0.3.1.dist-info/entry_points.txt
custodial_registration_proxy-0.3.1.dist-info/top_level.txt
custodial_registration_proxy-0.3.1.dist-info/RECORD
